foucluster/__init__.py
foucluster/cluster.py
foucluster/distance.py
foucluster/plot.py
foucluster/transform.py
foucluster-1.2.dist-info/LICENSE
foucluster-1.2.dist-info/METADATA
foucluster-1.2.dist-info/WHEEL
foucluster-1.2.dist-info/top_level.txt
foucluster-1.2.dist-info/RECORD
